fiberis/__init__.py
fiberis/analyzer/__init__.py
fiberis/analyzer/Data1D/Data1D_Gauge.py
fiberis/analyzer/Data1D/Data1D_MOOSEps.py
fiberis/analyzer/Data1D/Data1D_PumpingCurve.py
fiberis/analyzer/Data1D/__init__.py
fiberis/analyzer/Data1D/core1D.py
fiberis/analyzer/Data1DG/__init__.py
fiberis/analyzer/Data1DG/core1DG.py
fiberis/analyzer/Data2D/Data2D_XT_DSS.py
fiberis/analyzer/Data2D/__init__.py
fiberis/analyzer/Data2D/core2D.py
fiberis/analyzer/Data3D/Data3D_microseismic.py
fiberis/analyzer/Data3D/__init__.py
fiberis/analyzer/Data3D/core3D.py
fiberis/analyzer/Geometry3D/DataG3D_md.py
fiberis/analyzer/Geometry3D/__init__.py
fiberis/analyzer/Geometry3D/coreG3D.py
fiberis/analyzer/TensorProcessor/__init__.py
fiberis/analyzer/TensorProcessor/coreT.py
fiberis/io/__init__.py
fiberis/io/core.py
fiberis/io/reader_MOOSEcsv_pp1d.py
fiberis/io/reader_hfts2_h5.py
fiberis/io/reader_mariner_3d.py
fiberis/io/reader_mariner_das2d.py
fiberis/io/reader_mariner_dssh5.py
fiberis/io/reader_mariner_fiberdata_production_dat2d.py
fiberis/io/reader_mariner_gauge1d.py
fiberis/io/reader_mariner_pp1d.py
fiberis/io/reader_mariner_pressureg1.py
fiberis/io/reader_mariner_rfs_abandoned.py
fiberis/io/reader_moose_ps.py
fiberis/io/reader_moose_vpp.py
fiberis/moose/__init__.py
fiberis/moose/config.py
fiberis/moose/input_generator.py
fiberis/moose/model_builder.py
fiberis/moose/optimizer.py
fiberis/moose/postprocessor.py
fiberis/moose/runner.py
fiberis/simulator/core/__init__.py
fiberis/simulator/core/bcs.py
fiberis/simulator/core/pds.py
fiberis/simulator/optimizer/__init__.py
fiberis/simulator/optimizer/tso.py
fiberis/simulator/solver/PDESolver_EXP.py
fiberis/simulator/solver/PDESolver_IMP.py
fiberis/simulator/solver/__init__.py
fiberis/simulator/solver/matbuilder.py
fiberis/utils/__init__.py
fiberis/utils/history_utils.py
fiberis/utils/io_utils.py
fiberis/utils/mesh_utils.py
fiberis/utils/signal_utils.py
fiberis/utils/syn_utils.py
fiberis/utils/viz_utils.py
fiberis-0.3.0.dist-info/licenses/LICENSE
fiberis-0.3.0.dist-info/METADATA
fiberis-0.3.0.dist-info/WHEEL
fiberis-0.3.0.dist-info/top_level.txt
fiberis-0.3.0.dist-info/RECORD
